pgn_parser/__init__.py
pgn_parser/parser.py
pgn_parser/pgn.py
pgn_parser-1.1.0.dist-info/LICENSE
pgn_parser-1.1.0.dist-info/METADATA
pgn_parser-1.1.0.dist-info/WHEEL
pgn_parser-1.1.0.dist-info/top_level.txt
pgn_parser-1.1.0.dist-info/RECORD
