Metadata-Version: 2.1
Name: pgn-parser
Version: 1.1.0
Summary: PGN Parser is for parsing .pgn chess files
Home-page: https://github.com/brettbates/pgn_parser
Author: Brett Bates
Author-email: b@bmb.io
License: UNKNOWN
Platform: UNKNOWN
Classifier: Programming Language :: Python :: 3
Classifier: License :: OSI Approved :: MIT License
Classifier: Operating System :: OS Independent
